napari_properties_viewer/__init__.py
napari_properties_viewer/_hookimpl.py
napari_properties_viewer/_version.py
napari_properties_viewer/qt_properties_table.py
napari_properties_viewer/table_models.py
napari_properties_viewer/utils.py
napari_properties_viewer/_tests/__init__.py
napari_properties_viewer/_tests/test_napari_properties_viewer.py
napari_properties_viewer-0.0.2.dist-info/LICENSE
napari_properties_viewer-0.0.2.dist-info/METADATA
napari_properties_viewer-0.0.2.dist-info/WHEEL
napari_properties_viewer-0.0.2.dist-info/entry_points.txt
napari_properties_viewer-0.0.2.dist-info/top_level.txt
napari_properties_viewer-0.0.2.dist-info/RECORD
